rtl/util/top.sv
/****** alu.sv ******/
typedef enum logic [1:0] {
     add     = 2'h1,
     sub     = 2'h2,
     nop     = 2'h0
} operation_t /*verilator public*/;

module top #(
        parameter WIDTH = 6
) (
        input clk,
        input rst,

        input  operation_t  op_in,
        input  [WIDTH-1:0]  a_in,
        input  [WIDTH-1:0]  b_in,
        input               in_valid,

        output logic [WIDTH-1:0]  out,
        output logic              out_valid
);

        operation_t  op_in_r;
        logic  [WIDTH-1:0]  a_in_r;
        logic  [WIDTH-1:0]  b_in_r;
        logic               in_valid_r;
        logic  [WIDTH-1:0]  result;

        // Register all inputs
        always_ff @ (posedge clk, posedge rst) begin
                if (rst) begin
                        op_in_r     <= '0;
                        a_in_r      <= '0;
                        b_in_r      <= '0;
                        in_valid_r  <= '0;
                end else begin
                        op_in_r    <= op_in;
                        a_in_r     <= a_in;
                        b_in_r     <= b_in;
                        in_valid_r <= in_valid;
                end
        end

        // Compute the result
        always_comb begin
                result = '0;
                if (in_valid_r) begin
                        case (op_in_r)
                                add: result = a_in_r + b_in_r;
                                sub: result = a_in_r + (~b_in_r+1'b1);
                                default: result = '0;
                        endcase
                end
        end

        // Register outputs
        always_ff @ (posedge clk, posedge rst) begin
                if (rst) begin
                        out       <= '0;
                        out_valid <= '0;
                end else begin
                        out       <= result;
                        out_valid <= in_valid_r;
                end
        end

endmodule;

rtl/verilator/waveform.vcd
$version Generated by VerilatedVcd $end
$date Mon May  5 20:02:52 2025 $end
$timescale 1ps $end

 $scope module TOP $end
  $var wire  6 + a_in [5:0] $end
  $var wire  6 , b_in [5:0] $end
  $var wire  1 ( clk $end
  $var wire  1 - in_valid $end
  $var wire  2 * op_in [1:0] $end
  $var wire  6 . out [5:0] $end
  $var wire  1 / out_valid $end
  $var wire  1 ) rst $end
  $scope module top $end
   $var wire 32 0 WIDTH [31:0] $end
   $var wire  6 + a_in [5:0] $end
   $var wire  6 $ a_in_r [5:0] $end
   $var wire  6 , b_in [5:0] $end
   $var wire  6 % b_in_r [5:0] $end
   $var wire  1 ( clk $end
   $var wire  1 - in_valid $end
   $var wire  1 & in_valid_r $end
   $var wire  2 * op_in [1:0] $end
   $var wire  2 # op_in_r [1:0] $end
   $var wire  6 . out [5:0] $end
   $var wire  1 / out_valid $end
   $var wire  6 ' result [5:0] $end
   $var wire  1 ) rst $end
  $upscope $end
 $upscope $end
$enddefinitions $end


#0
b00 #
b000000 $
b000000 %
0&
b000000 '
1(
0)
b00 *
b000000 +
b000000 ,
0-
b000000 .
0/
b00000000000000000000000000000110 0
#1
0(
b000111 +
b000110 ,
1-
#2
b000111 $
b000110 %
1&
1(
#3
0(
b01 *
b010001 +
b011111 ,
0-
#4
b01 #
b010001 $
b011111 %
0&
1(
1/
#5
0(
b10 *
b001001 +
b001101 ,
1-
#6
b10 #
b001001 $
b001101 %
1&
b111100 '
1(
0/
#7
0(
b010010 +
b011011 ,
0-
#8
b010010 $
b011011 %
0&
b000000 '
1(
b111100 .
1/
#9
0(
b01 *
b011100 +
b000010 ,
#10
b01 #
b011100 $
b000010 %
1(
b000000 .
0/
#11
0(
b00 *
b011011 +
b001000 ,
1-
#12
b00 #
b011011 $
b001000 %
1&
1(
#13
0(
b10 *
b010110 +
b011010 ,
#14
b10 #
b010110 $
b011010 %
b111100 '
1(
1/
#15
0(
b010011 +
b011111 ,
0-
#16
b010011 $
b011111 %
0&
b000000 '
1(
b111100 .
#17
0(
b000110 +
b010010 ,
1-
#18
b000110 $
b010010 %
1&
b110100 '
1(
b000000 .
0/
#19
0(
b01 *
b010001 +
b011000 ,
0-
#20
b01 #
b010001 $
b011000 %
0&
b000000 '
1(
b110100 .
1/
#21
0(
b00 *
b000101 +
b011101 ,
1-
#22
b00 #
b000101 $
b011101 %
1&
1(
b000000 .
0/
#23
0(
b10 *
b011000 +
b001001 ,
0-
#24
b10 #
b011000 $
b001001 %
0&
1(
1/
#25
0(
b001011 +
b010010 ,
#26
b001011 $
b010010 %
1(
0/
#27
0(
b011011 +
b010100 ,
1-
#28
b011011 $
b010100 %
1&
b000111 '
1(
#29
0(
b01 *
b001110 +
b000010 ,
#30
b01 #
b001110 $
b000010 %
b010000 '
1(
b000111 .
1/
#31
0(
b10 *
b000001 +
b011101 ,
#32
b10 #
b000001 $
b011101 %
b100100 '
1(
b010000 .
#33
0(
b01 *
b010000 +
b001001 ,
#34
b01 #
b010000 $
b001001 %
b011001 '
1(
b100100 .
#35
0(
b00 *
b000001 +
b000001 ,
#36
b00 #
b000001 $
b000001 %
b000000 '
1(
b011001 .
#37
0(
b10 *
b011110 +
#38
b10 #
b011110 $
b011101 '
1(
b000000 .
#39
0(
b00 *
b001010 +
b011100 ,
0-
#40
b00 #
b001010 $
b011100 %
0&
b000000 '
1(
b011101 .
#41
0(
b001111 +
b011000 ,
#42
b001111 $
b011000 %
1(
b000000 .
0/
#43
0(
b001100 +
b010000 ,
1-
#44
b001100 $
b010000 %
1&
1(
#45
0(
b010010 +
b001111 ,
0-
#46
b010010 $
b001111 %
0&
1(
1/
#47
0(
b01 *
b001100 +
b011000 ,
#48
b01 #
b001100 $
b011000 %
1(
0/
#49
0(
b00 *
b000010 +
b011010 ,
1-
#50
b00 #
b000010 $
b011010 %
1&
1(
#51
0(
b10 *
b011011 +
0-
#52
b10 #
b011011 $
0&
1(
1/
#53
0(
b001001 ,
#54
b001001 %
1(
0/
#55
0(
b01 *
b000101 +
b011100 ,
#56
b01 #
b000101 $
b011100 %
1(
#57
0(
b10 *
b010101 +
b011000 ,
1-
#58
b10 #
b010101 $
b011000 %
1&
b111101 '
1(
#59
0(
b01 *
b001001 +
b011001 ,
#60
b01 #
b001001 $
b011001 %
b100010 '
1(
b111101 .
1/
#61
0(
b00 *
b001000 +
#62
b00 #
b001000 $
b000000 '
1(
b100010 .
#63
0(
b010001 +
b001011 ,
#64
b010001 $
b001011 %
1(
b000000 .
#65
0(
b000101 +
b001111 ,
0-
#66
b000101 $
b001111 %
0&
1(
#67
0(
b001001 +
b000001 ,
1-
#68
b001001 $
b000001 %
1&
1(
0/
#69
0(
b10 *
b001010 +
b001011 ,
0-
#70
b10 #
b001010 $
b001011 %
0&
1(
1/
#71
0(
b001000 +
b000111 ,
1-
#72
b001000 $
b000111 %
1&
b000001 '
1(
0/
#73
0(
b00 *
b011111 +
b000011 ,
0-
#74
b00 #
b011111 $
b000011 %
0&
b000000 '
1(
b000001 .
1/
#75
0(
b01 *
b011100 +
b011011 ,
1-
#76
b01 #
b011100 $
b011011 %
1&
b110111 '
1(
b000000 .
0/
#77
0(
b10 *
b010100 +
b010011 ,
#78
b10 #
b010100 $
b010011 %
b000001 '
1(
b110111 .
1/
#79
0(
b01 *
b011110 +
b001011 ,
#80
b01 #
b011110 $
b001011 %
b101001 '
1(
b000001 .
#81
0(
b10 *
b011011 +
b010000 ,
0-
#82
b10 #
b011011 $
b010000 %
0&
b000000 '
1(
b101001 .
#83
0(
b01 *
b010001 +
b011110 ,
#84
b01 #
b010001 $
b011110 %
1(
b000000 .
0/
#85
0(
b00 *
b001010 +
b010100 ,
#86
b00 #
b001010 $
b010100 %
1(
#87
0(
b011011 +
b010000 ,
1-
#88
b011011 $
b010000 %
1&
1(
#89
0(
b010011 +
b001101 ,
0-
#90
b010011 $
b001101 %
0&
1(
1/
#91
0(
b10 *
b001000 +
b000111 ,
#92
b10 #
b001000 $
b000111 %
1(
0/
#93
0(
b00 *
b011011 +
b001111 ,
1-
#94
b00 #
b011011 $
b001111 %
1&
1(
#95
0(
b10 *
b011010 +
b011011 ,
#96
b10 #
b011010 $
b011011 %
b111111 '
1(
1/
#97
0(
b001011 +
b000001 ,
0-
#98
b001011 $
b000001 %
0&
b000000 '
1(
b111111 .
#99
0(
b00 *
b011111 +
b000011 ,
1-
#100
b00 #
b011111 $
b000011 %
1&
1(
b000000 .
0/
#101
0(
b01 *
b011000 +
b000100 ,
#102
b01 #
b011000 $
b000100 %
b011100 '
1(
1/
#103
0(
b10 *
b010101 +
b001010 ,
0-
#104
b10 #
b010101 $
b001010 %
0&
b000000 '
1(
b011100 .
#105
0(
b00 *
b011000 +
b010010 ,
#106
b00 #
b011000 $
b010010 %
1(
b000000 .
0/
#107
0(
b10 *
b011001 +
b001101 ,
#108
b10 #
b011001 $
b001101 %
1(
#109
0(
b00 *
b011100 +
b011111 ,
1-
#110
b00 #
b011100 $
b011111 %
1&
1(
#111
0(
b01 *
b011010 +
b001011 ,
#112
b01 #
b011010 $
b001011 %
b100101 '
1(
1/
#113
0(
b10 *
b001100 +
b000110 ,
#114
b10 #
b001100 $
b000110 %
b000110 '
1(
b100101 .
#115
0(
b00 *
b001010 +
b011010 ,
0-
#116
b00 #
b001010 $
b011010 %
0&
b000000 '
1(
b000110 .
#117
0(
b01 *
b011110 +
b010000 ,
1-
#118
b01 #
b011110 $
b010000 %
1&
b101110 '
1(
b000000 .
0/
#119
0(
b10 *
b011011 +
b000100 ,
#120
b10 #
b011011 $
b000100 %
b010111 '
1(
b101110 .
1/
#121
0(
b010110 +
b010100 ,
#122
b010110 $
b010100 %
b000010 '
1(
b010111 .
#123
0(
b01 *
b000010 +
b010000 ,
0-
#124
b01 #
b000010 $
b010000 %
0&
b000000 '
1(
b000010 .
#125
0(
b00 *
b001111 +
b010010 ,
1-
#126
b00 #
b001111 $
b010010 %
1&
1(
b000000 .
0/
#127
0(
b01 *
b011101 +
b000010 ,
#128
b01 #
b011101 $
b000010 %
b011111 '
1(
1/
#129
0(
b001000 +
b010000 ,
0-
#130
b001000 $
b010000 %
0&
b000000 '
1(
b011111 .
#131
0(
b10 *
b001010 +
b001001 ,
#132
b10 #
b001010 $
b001001 %
1(
b000000 .
0/
#133
0(
b011010 +
b001010 ,
1-
#134
b011010 $
b001010 %
1&
b010000 '
1(
#135
0(
b00 *
b001110 +
b011000 ,
0-
#136
b00 #
b001110 $
b011000 %
0&
b000000 '
1(
b010000 .
1/
#137
0(
b001100 +
b011011 ,
#138
b001100 $
b011011 %
1(
b000000 .
0/
#139
0(
b010111 ,
1-
#140
b010111 %
1&
1(
#141
0(
b01 *
b001001 +
b000010 ,
0-
#142
b01 #
b001001 $
b000010 %
0&
1(
1/
#143
0(
b000100 +
b010011 ,
1-
#144
b000100 $
b010011 %
1&
b010111 '
1(
0/
#145
0(
b00 *
b000011 +
b000100 ,
#146
b00 #
b000011 $
b000100 %
b000000 '
1(
b010111 .
1/
#147
0(
b10 *
b001101 +
b010100 ,
#148
b10 #
b001101 $
b010100 %
b111001 '
1(
b000000 .
#149
0(
b011110 +
b010010 ,
0-
#150
b011110 $
b010010 %
0&
b000000 '
1(
b111001 .
#151
0(
b00 *
b001010 +
b000100 ,
#152
b00 #
b001010 $
b000100 %
1(
b000000 .
0/
#153
0(
b000000 +
b000011 ,
#154
b000000 $
b000011 %
1(
#155
0(
b10 *
b011011 +
b010010 ,
#156
b10 #
b011011 $
b010010 %
1(
#157
0(
b00 *
b010100 +
b001100 ,
1-
#158
b00 #
b010100 $
b001100 %
1&
1(
#159
0(
b000000 +
b011010 ,
#160
b000000 $
b011010 %
1(
1/
#161
0(
b01 *
b011110 +
b000101 ,
0-
#162
b01 #
b011110 $
b000101 %
0&
1(
#163
0(
b10 *
b011001 +
b000111 ,
1-
#164
b10 #
b011001 $
b000111 %
1&
b010010 '
1(
0/
#165
0(
b01 *
b010000 ,
#166
b01 #
b010000 %
b101001 '
1(
b010010 .
1/
#167
0(
b10 *
b010100 +
b010011 ,
0-
#168
b10 #
b010100 $
b010011 %
0&
b000000 '
1(
b101001 .
#169
0(
b00 *
b010111 +
b011110 ,
#170
b00 #
b010111 $
b011110 %
1(
b000000 .
0/
#171
0(
b01 *
b010000 +
b001000 ,
1-
#172
b01 #
b010000 $
b001000 %
1&
b011000 '
1(
#173
0(
b00 *
b010100 +
b000001 ,
0-
#174
b00 #
b010100 $
b000001 %
0&
b000000 '
1(
b011000 .
1/
#175
0(
b10 *
b011100 +
b000100 ,
#176
b10 #
b011100 $
b000100 %
1(
b000000 .
0/
#177
0(
b001001 +
b001001 ,
1-
#178
b001001 $
b001001 %
1&
1(
#179
0(
b010000 +
b011010 ,
#180
b010000 $
b011010 %
b110110 '
1(
1/
#181
0(
b00 *
b001010 +
b011110 ,
0-
#182
b00 #
b001010 $
b011110 %
0&
b000000 '
1(
b110110 .
#183
0(
b010001 +
b000101 ,
#184
b010001 $
b000101 %
1(
b000000 .
0/
#185
0(
b10 *
b000100 +
b010011 ,
#186
b10 #
b000100 $
b010011 %
1(
#187
0(
b00 *
b011011 +
b010001 ,
#188
b00 #
b011011 $
b010001 %
1(
#189
0(
b01 *
b010010 +
b010111 ,
#190
b01 #
b010010 $
b010111 %
1(
#191
0(
b011011 +
b011100 ,
1-
#192
b011011 $
b011100 %
1&
b110111 '
1(
#193
0(
b10 *
b000101 +
b001111 ,
#194
b10 #
b000101 $
b001111 %
b110110 '
1(
b110111 .
1/
#195
0(
b00 *
b001001 +
b000010 ,
#196
b00 #
b001001 $
b000010 %
b000000 '
1(
b110110 .
#197
0(
b01 *
b000000 +
b001010 ,
0-
#198
b01 #
b000000 $
b001010 %
0&
1(
b000000 .
#199
0(
b00 *
b010000 +
b000101 ,
